{
    "promotionRule":  "Promote only if endpoint is mounted, guard behavior proven, and happy+forbidden/invalid tests pass.",
    "maxPromotions":  10,
    "batchType":  "auto.read.courses.extended",
    "featureIds":  [
                       "auto.get.certificates",
                       "auto.get.courses.param.recommendations",
                       "auto.get.courses.param.enrollment.status",
                       "auto.get.courses.category.param",
                       "auto.get.courses.mine",
                       "auto.get.courses.subcategories.param",
                       "auto.get.courses.trending.tags",
                       "auto.get.courses.user.certificates",
                       "auto.get.courses.verify.param",
                       "auto.get.debug.info"
                   ],
    "repo":  "backend",
    "cycle":  "2026-02-25 / 16",
    "notes":  "Cycle 16 high-confidence read batch."
}
